    "type": "FeatureCollection",    "totalFeatures": 3,    "features": [{        "type": "Feature",        "id": "prova.1",        "geometry": {            "type": "Point",            "coordinates": [11.1515, 43.4613]        },        "geometry_name": "the_geom",        "properties": {            "ID": 1,            "ID_PUTT": 0,            "DENOMINAZ": "Fortezza di Poggio Imperiale a Poggibonsi",            "TIP_BENE": "C",            "CATEGORIA": "Bene architettonico",            "ATTR_BENE": "Vincolato",            "FONTE": "Sovrintendenza",            "PROVVED": "D.M. 11.2.1980",            "D_CATAST": "FG. 13 p.lla 871-1357",            "PROPRIET": "Demaniale",            "COD_PROP": "P",            "NOTE": "da documentare",            "COMUNE": "Poggibonsi",            "TIPBCPTCP": "C_CU"        }    }, {        "type": "Feature",        "id": "prova.2",        "geometry": {            "type": "Point",            "coordinates": [11.0802, 43.1199]        },        "geometry_name": "the_geom",        "properties": {            "ID": 59023,            "ID_PUTT": 0,            "DENOMINAZ": "Castello di Miranduolo",            "TIP_BENE": "C",            "CATEGORIA": "Bene architettonico",            "ATTR_BENE": "Vincolato",            "FONTE": "Sovrintendenza",            "PROVVED": "D.M. 20.2.1981",            "D_CATAST": "FG. 63/A p.lla 836-830",            "PROPRIET": "Privata",            "COD_PROP": "Pr",            "NOTE": "da documentare",            "COMUNE": "Vico del Gargano",            "TIPBCPTCP": "C_CU"        }    }, {        "type": "Feature",        "id": "castelli.3",        "geometry": {            "type": "Point",            "coordinates": [11.3316, 43.3185]        },        "geometry_name": "the_geom",        "properties": {            "ID": 56002,            "ID_PUTT": 1,            "DENOMINAZ": "Siena, spazio urbano",            "TIP_BENE": "C",            "CATEGORIA": "Bene architettonico",            "ATTR_BENE": "Vincolato",            "FONTE": "PUTT",            "PROVVED": "D.M. 10.7.1987",            "D_CATAST": "FG. 98 p.lla 8(parte)",            "PROPRIET": "Privata",            "COD_PROP": "Pr",            "NOTE": "da documentare",            "COMUNE": "Torremaggiore",            "TIPBCPTCP": "C"        }    }],    "crs": {        "type": "name",        "properties": {            "name": "urn:ogc:def:crs:EPSG::4326"        }    }